restful_checker/__init__.py
restful_checker/__main__.py
restful_checker/main.py
restful_checker/checks/__init__.py
restful_checker/checks/check_error_format.py
restful_checker/checks/check_result.py
restful_checker/checks/content_type_checker.py
restful_checker/checks/http_method_checker.py
restful_checker/checks/https_checker.py
restful_checker/checks/naming_checker.py
restful_checker/checks/pagination_checker.py
restful_checker/checks/param_consistency_checker.py
restful_checker/checks/query_filter_checker.py
restful_checker/checks/resource_nesting_checker.py
restful_checker/checks/response_example_checker.py
restful_checker/checks/status_code_checker.py
restful_checker/checks/version_checker.py
restful_checker/data/__init__.py
restful_checker/data/style.css
restful_checker/engine/__init__.py
restful_checker/engine/analyzer.py
restful_checker/engine/openapi_loader.py
restful_checker/engine/path_grouper.py
restful_checker/report/__init__.py
restful_checker/report/extract_json_from_html.py
restful_checker/report/html_report.py
restful_checker/report/rest_docs.py
restful_checker/tools/__init__.py
restful_checker/tools/help_restful_checker.py
restful_checker-3.0.1.dist-info/licenses/LICENSE
restful_checker-3.0.1.dist-info/METADATA
restful_checker-3.0.1.dist-info/WHEEL
restful_checker-3.0.1.dist-info/entry_points.txt
restful_checker-3.0.1.dist-info/top_level.txt
restful_checker-3.0.1.dist-info/RECORD
