Metadata-Version: 2.4
Name: restful-checker
Version: 3.0.1
Summary: Check RESTful API compliance from OpenAPI definitions and generate HTML reports
Author: Javier Lianes García
Author-email: jlianesglr@gmail.com
Project-URL: GitHub, https://github.com/JaviLianes8/restful-checker
Project-URL: LinkedIn, https://www.linkedin.com/in/jlianes/
Classifier: Programming Language :: Python :: 3
Classifier: License :: OSI Approved :: MIT License
Classifier: Operating System :: OS Independent
Requires-Python: >=3.7
License-File: LICENSE
Requires-Dist: pyyaml
Requires-Dist: requests
Requires-Dist: beautifulsoup4
Dynamic: author
Dynamic: author-email
Dynamic: classifier
Dynamic: description
Dynamic: description-content-type
Dynamic: license-file
Dynamic: project-url
Dynamic: requires-dist
Dynamic: requires-python
Dynamic: summary
